character_extractor/__init__.py
character_extractor/__main__.py
character_extractor/main.py
character_extractor-0.1.2.dist-info/METADATA
character_extractor-0.1.2.dist-info/WHEEL
character_extractor-0.1.2.dist-info/entry_points.txt
character_extractor-0.1.2.dist-info/top_level.txt
character_extractor-0.1.2.dist-info/RECORD
